pychloride/__init__.py
pychloride/libsodium.so
pychloride-0.7.18.1.dist-info/METADATA
pychloride-0.7.18.1.dist-info/WHEEL
pychloride-0.7.18.1.dist-info/licenses/LICENSE
pychloride-0.7.18.1.dist-info/licenses/THIRD_PARTY_LICENSES.md
pychloride-0.7.18.1.dist-info/RECORD
