Metadata-Version: 2.4
Name: pychloride
Version: 0.7.18.1
Summary: Pyodide-compatible ctypes interface for libsodium (refactored pysodium)
Project-URL: Homepage, https://github.com/WebOfTrust/pychloride
Project-URL: Repository, https://github.com/WebOfTrust/pychloride.git
Author-email: Stefan Marsiske <s@ctrlc.hu>, Evan Asakawa <evanja57@gmail.com>
License: BSD 2-Clause License
License-File: LICENSE
License-File: THIRD_PARTY_LICENSES.md
Keywords: API,NaCl,cryptography,libsodium,pyodide,wasm
Classifier: Development Status :: 4 - Beta
Classifier: License :: OSI Approved :: BSD License
Classifier: Programming Language :: Python :: 3
Classifier: Programming Language :: Python :: 3.9
Classifier: Programming Language :: Python :: 3.10
Classifier: Programming Language :: Python :: 3.11
Classifier: Programming Language :: Python :: 3.12
Classifier: Topic :: Security
Classifier: Topic :: Security :: Cryptography
Requires-Python: >=3.9
Provides-Extra: dev
Requires-Dist: pytest>=7.0; extra == 'dev'
